hplc_data_analysis/__init__.py
hplc_data_analysis/fragmenter.py
hplc_data_analysis/hplc.py
hplc_data_analysis/pubchem.py
hplc_data_analysis-2.0.0.dist-info/METADATA
hplc_data_analysis-2.0.0.dist-info/WHEEL
hplc_data_analysis-2.0.0.dist-info/top_level.txt
hplc_data_analysis-2.0.0.dist-info/RECORD
