Metadata-Version: 2.1
Name: hplc_data_analysis
Version: 2.0.0
Summary: Tool for automatic analysis of multiple HPLC results
Author: Matteo Pecchi
License: MIT
Project-URL: Homepage, https://github.com/mpecchi/hplc_data_analysis
Project-URL: Documentation, https://hplc-data-analysis.readthedocs.io/en/latest/
Classifier: Programming Language :: Python :: 3
Classifier: License :: OSI Approved :: MIT License
Classifier: Operating System :: OS Independent
Requires-Python: >=3.8
Requires-Dist: pathlib
Requires-Dist: numpy
Requires-Dist: pandas
Requires-Dist: matplotlib
Requires-Dist: seaborn
Requires-Dist: ele
Requires-Dist: pubchempy
Requires-Dist: rdkit
Requires-Dist: openpyxl
Requires-Dist: pyarrow
Requires-Dist: myfigure
